llama_index/readers/document360/__init__.py
llama_index/readers/document360/base.py
llama_index/readers/document360/errors.py
llama_index/readers/document360/entities/__init__.py
llama_index/readers/document360/entities/article.py
llama_index/readers/document360/entities/article_slim.py
llama_index/readers/document360/entities/category.py
llama_index/readers/document360/entities/project_version.py
llama_index_readers_document360-0.3.1.dist-info/METADATA
llama_index_readers_document360-0.3.1.dist-info/WHEEL
llama_index_readers_document360-0.3.1.dist-info/licenses/LICENSE
llama_index_readers_document360-0.3.1.dist-info/RECORD
